{
  "nodes": [
    { "id": "plan:notification-feature", "type": "plan", "title": "알림 기능 기획", "file": "plans/notification-feature.html" },
    { "id": "domain:notification", "type": "domain", "title": "알림 도메인" },
    { "id": "feature:in-app-notification-center", "type": "feature", "title": "인앱 알림센터", "plan": "plan:notification-feature" },
    { "id": "feature:notification-read-status", "type": "feature", "title": "알림 읽음 처리", "plan": "plan:notification-feature" },
    { "id": "feature:web-push", "type": "feature", "title": "웹 푸시", "plan": "plan:notification-feature", "status": "deferred" },
    { "id": "feature:notification-preferences", "type": "feature", "title": "알림 on/off 설정", "plan": "plan:notification-feature" },
    { "id": "wireframe:notification-feature", "type": "wireframe", "title": "알림 기능 와이어프레임", "file": "wireframes/notification-feature.html" },

    { "id": "issue:NOTI-1", "type": "issue", "title": "알림 데이터 모델 및 저장 API 설계", "file": "issues/notification-feature.html", "priority": "P0", "size": "S" },
    { "id": "issue:NOTI-2", "type": "issue", "title": "실시간 알림 전달 채널 구축", "file": "issues/notification-feature.html", "priority": "P0", "size": "M" },
    { "id": "issue:NOTI-3", "type": "issue", "title": "헤더 벨 아이콘 + 미확인 개수 뱃지", "file": "issues/notification-feature.html", "priority": "P0", "size": "S" },
    { "id": "issue:NOTI-4", "type": "issue", "title": "알림 목록 UI (알림센터)", "file": "issues/notification-feature.html", "priority": "P0", "size": "M" },
    { "id": "issue:NOTI-5", "type": "issue", "title": "알림 클릭 시 대상 화면으로 이동 (딥링크)", "file": "issues/notification-feature.html", "priority": "P1", "size": "S" },

    { "id": "issue:NOTI-6", "type": "issue", "title": "개별 알림 읽음 처리", "file": "issues/notification-feature.html", "priority": "P0", "size": "S" },
    { "id": "issue:NOTI-7", "type": "issue", "title": "모두 읽음 일괄 처리", "file": "issues/notification-feature.html", "priority": "P1", "size": "S" },
    { "id": "issue:NOTI-8", "type": "issue", "title": "읽음 상태 세션/기기 간 일관성 검증", "file": "issues/notification-feature.html", "priority": "P1", "size": "S" },

    { "id": "issue:NOTI-9", "type": "issue", "title": "웹 푸시 발송 인프라 선정 및 서버 기반 구축", "file": "issues/notification-feature.html", "priority": "P1", "size": "L", "status": "deferred" },
    { "id": "issue:NOTI-10", "type": "issue", "title": "브라우저 푸시 권한 요청 및 구독 등록/해제", "file": "issues/notification-feature.html", "priority": "P1", "size": "M", "status": "deferred" },
    { "id": "issue:NOTI-11", "type": "issue", "title": "Service Worker 푸시 수신 및 클릭 시 화면 진입", "file": "issues/notification-feature.html", "priority": "P1", "size": "M", "status": "deferred" },
    { "id": "issue:NOTI-12", "type": "issue", "title": "푸시 미지원 브라우저 안내 UX", "file": "issues/notification-feature.html", "priority": "P2", "size": "S", "status": "deferred" },

    { "id": "issue:NOTI-13", "type": "issue", "title": "알림 유형별 on/off 설정 UI 및 API (인앱 채널)", "file": "issues/notification-feature.html", "priority": "P2", "size": "M" },
    { "id": "issue:NOTI-14", "type": "issue", "title": "off 설정 유형에 대한 발송 차단 적용 (인앱 채널)", "file": "issues/notification-feature.html", "priority": "P2", "size": "S" }
  ],
  "edges": [
    { "from": "plan:notification-feature", "to": "domain:notification", "rel": "touches" },
    { "from": "feature:in-app-notification-center", "to": "domain:notification", "rel": "belongs_to" },
    { "from": "feature:notification-read-status", "to": "domain:notification", "rel": "belongs_to" },
    { "from": "feature:web-push", "to": "domain:notification", "rel": "belongs_to" },
    { "from": "feature:notification-preferences", "to": "domain:notification", "rel": "belongs_to" },

    { "from": "wireframe:notification-feature", "to": "feature:in-app-notification-center", "rel": "visualizes" },
    { "from": "wireframe:notification-feature", "to": "feature:notification-read-status", "rel": "visualizes" },
    { "from": "wireframe:notification-feature", "to": "feature:web-push", "rel": "visualizes" },
    { "from": "wireframe:notification-feature", "to": "feature:notification-preferences", "rel": "visualizes" },

    { "from": "issue:NOTI-1", "to": "feature:in-app-notification-center", "rel": "implements" },
    { "from": "issue:NOTI-2", "to": "feature:in-app-notification-center", "rel": "implements" },
    { "from": "issue:NOTI-3", "to": "feature:in-app-notification-center", "rel": "implements" },
    { "from": "issue:NOTI-4", "to": "feature:in-app-notification-center", "rel": "implements" },
    { "from": "issue:NOTI-5", "to": "feature:in-app-notification-center", "rel": "implements" },

    { "from": "issue:NOTI-6", "to": "feature:notification-read-status", "rel": "implements" },
    { "from": "issue:NOTI-7", "to": "feature:notification-read-status", "rel": "implements" },
    { "from": "issue:NOTI-8", "to": "feature:notification-read-status", "rel": "implements" },

    { "from": "issue:NOTI-9", "to": "feature:web-push", "rel": "implements" },
    { "from": "issue:NOTI-10", "to": "feature:web-push", "rel": "implements" },
    { "from": "issue:NOTI-11", "to": "feature:web-push", "rel": "implements" },
    { "from": "issue:NOTI-12", "to": "feature:web-push", "rel": "implements" },

    { "from": "issue:NOTI-13", "to": "feature:notification-preferences", "rel": "implements" },
    { "from": "issue:NOTI-14", "to": "feature:notification-preferences", "rel": "implements" },

    { "from": "issue:NOTI-2", "to": "issue:NOTI-1", "rel": "depends_on" },
    { "from": "issue:NOTI-3", "to": "issue:NOTI-2", "rel": "depends_on" },
    { "from": "issue:NOTI-4", "to": "issue:NOTI-1", "rel": "depends_on" },
    { "from": "issue:NOTI-5", "to": "issue:NOTI-4", "rel": "depends_on" },
    { "from": "issue:NOTI-6", "to": "issue:NOTI-4", "rel": "depends_on" },
    { "from": "issue:NOTI-7", "to": "issue:NOTI-6", "rel": "depends_on" },
    { "from": "issue:NOTI-8", "to": "issue:NOTI-6", "rel": "depends_on" },
    { "from": "issue:NOTI-10", "to": "issue:NOTI-9", "rel": "depends_on" },
    { "from": "issue:NOTI-11", "to": "issue:NOTI-10", "rel": "depends_on" },
    { "from": "issue:NOTI-11", "to": "issue:NOTI-5", "rel": "depends_on" },
    { "from": "issue:NOTI-12", "to": "issue:NOTI-10", "rel": "depends_on" },
    { "from": "issue:NOTI-13", "to": "issue:NOTI-1", "rel": "depends_on" },
    { "from": "issue:NOTI-14", "to": "issue:NOTI-13", "rel": "depends_on" },
    { "from": "issue:NOTI-14", "to": "issue:NOTI-2", "rel": "depends_on" }
  ]
}
